<?xml version="1.0" encoding="UTF-8"?>
<databaseChangeLog
        xmlns="http://www.liquibase.org/xml/ns/dbchangelog"
        xmlns:xsi="http://www.w3.org/2001/XMLSchema-instance"
        xsi:schemaLocation="http://www.liquibase.org/xml/ns/dbchangelog
        http://www.liquibase.org/xml/ns/dbchangelog/dbchangelog-3.1.xsd">

    <changeSet id="add_column_custom_report" author="sheng.w">

        <addColumn tableName="custom_report">
            <column name="front_end_name" type="varchar(255)">
                <constraints nullable="false"/>
            </column>
        </addColumn>

    </changeSet>

    <changeSet id="tag-cms-1.126" author="indira">
        <tagDatabase tag="cms-1.126" />
    </changeSet>
</databaseChangeLog>